drivtime/__init__.py
drivtime/class.py
drivtime-0.0.3.dist-info/LICENSE
drivtime-0.0.3.dist-info/METADATA
drivtime-0.0.3.dist-info/WHEEL
drivtime-0.0.3.dist-info/top_level.txt
drivtime-0.0.3.dist-info/RECORD
