Metadata-Version: 2.1
Name: drivtime
Version: 0.0.3
Summary: Driving time and rest periods in the road transport sector framework
Home-page: https://github.com/hugodscarvalho/drivtime
Author: Hugo Carvalho
Author-email: hugodanielsilvacarvalho.hc@gmail.com
License: UNKNOWN
Keywords: python,driving time,rest periods,EU,Regulation,road transport,truck,optimization,passenger transport,transport
Platform: UNKNOWN
Classifier: Programming Language :: Python :: 3
Classifier: License :: OSI Approved :: MIT License
Classifier: Operating System :: OS Independent
License-File: LICENSE
